{
    "$schema": "https://schema.management.azure.com/schemas/2015-01-01/deploymentTemplate.json#",
    "contentVersion": "1.0.0.0",
    "parameters": {
        "resourceName": {
            "type": "string",
			"defaultValue": "IgniteCluster",
            "metadata": {
                "description": "The name of the Managed Cluster resource."
            }
        },
        "location": {
            "type": "string",
			"defaultValue": "westus",
            "metadata": {
                "description": "The location of AKS resource."
            }
        },
        "dnsPrefix": {
            "type": "string",
			"defaultvValue": "IgniteCluster-dns",
            "metadata": {
                "description": "Optional DNS prefix to use with hosted Kubernetes API server FQDN."
            }
        },
        "agentCount": {
            "type": "int",
            "defaultValue": 2,
            "metadata": {
                "description": "The number of agent nodes for the cluster."
            },
            "minValue": 1,
            "maxValue": 100
        },
        "agentVMSize": {
            "type": "string",
            "defaultValue": "Standard_D2_v2",
            "metadata": {
                "description": "The size of the Virtual Machine."
            }
        },
        "osType": {
            "type": "string",
            "defaultValue": "Linux",
            "allowedValues": [
                "Linux"
            ],
            "metadata": {
                "description": "The type of operating system."
            }
        },
        "kubernetesVersion": {
            "type": "string",
            "defaultValue": "1.7.7",
            "metadata": {
                "description": "The version of Kubernetes."
            }
        },
        "networkPlugin": {
            "type": "string",
            "allowedValues": [
                "azure",
                "kubenet"
            ],
			"defaultValue": "kubenet",
            "metadata": {
                "description": "Network plugin used for building Kubernetes network."
            }
        },
        "enableRBAC": {
            "type": "bool",
            "defaultValue": true,
            "metadata": {
                "description": "Boolean flag to turn on and off of RBAC."
            }
        },
        "enableHttpApplicationRouting": {
            "type": "bool",
            "defaultValue": false,
            "metadata": {
                "description": "Boolean flag to turn on and off of http application routing."
            }
        }
    },
    "resources": [
        {
            "apiVersion": "2020-03-01",
            "dependsOn": [],
            "type": "Microsoft.ContainerService/managedClusters",
            "location": "[parameters('location')]",
            "name": "[parameters('resourceName')]",
            "properties": {
                "kubernetesVersion": "[parameters('kubernetesVersion')]",
                "enableRBAC": "[parameters('enableRBAC')]",
                "dnsPrefix": "[parameters('dnsPrefix')]",
                "agentPoolProfiles": [
                    {
                        "name": "agentpool",
                        "osDiskSizeGB": "[parameters('osDiskSizeGB')]",
                        "count": "[parameters('agentCount')]",
                        "vmSize": "[parameters('agentVMSize')]",
                        "osType": "[parameters('osType')]",
                        "storageProfile": "ManagedDisks",
                        "mode": "System",
                        "type": "VirtualMachineScaleSets"
                    }
                ],
                "servicePrincipalProfile": {
                    "ClientId": "[parameters('servicePrincipalClientId')]",
                    "Secret": "[parameters('servicePrincipalClientSecret')]",
                    "aadSessionKey": "[parameters('aadSessionKey')]"
                },
                "networkProfile": {
                    "loadBalancerSku": "standard",
                    "networkPlugin": "[parameters('networkPlugin')]"
                },
                "apiServerAccessProfile": {
                    "enablePrivateCluster": "[parameters('enablePrivateCluster')]"
                },
                "addonProfiles": {
                    "httpApplicationRouting": {
                        "enabled": "[parameters('enableHttpApplicationRouting')]"
                    },
                    "omsagent": {
                        "enabled": "[parameters('enableOmsAgent')]",
                        "config": {
                            "logAnalyticsWorkspaceResourceID": "[parameters('omsWorkspaceId')]"
                        }
                    }
                }
            },
            "tags": {}
        },
        {
            "type": "Microsoft.Resources/deployments",
            "name": "SolutionDeployment-20200420151910",
            "apiVersion": "2017-05-10",
            "resourceGroup": "[split(parameters('omsWorkspaceId'),'/')[4]]",
            "subscriptionId": "[split(parameters('omsWorkspaceId'),'/')[2]]",
            "properties": {
                "mode": "Incremental",
                "template": {
                    "$schema": "https://schema.management.azure.com/schemas/2015-01-01/deploymentTemplate.json#",
                    "contentVersion": "1.0.0.0",
                    "parameters": {},
                    "variables": {},
                    "resources": [
                        {
                            "apiVersion": "2015-11-01-preview",
                            "type": "Microsoft.OperationsManagement/solutions",
                            "location": "[parameters('workspaceRegion')]",
                            "name": "[concat('ContainerInsights', '(', split(parameters('omsWorkspaceId'),'/')[8], ')')]",
                            "properties": {
                                "workspaceResourceId": "[parameters('omsWorkspaceId')]"
                            },
                            "plan": {
                                "name": "[concat('ContainerInsights', '(', split(parameters('omsWorkspaceId'),'/')[8], ')')]",
                                "product": "[concat('OMSGallery/', 'ContainerInsights')]",
                                "promotionCode": "",
                                "publisher": "Microsoft"
                            }
                        }
                    ]
                }
            },
            "dependsOn": []
        }
    ],
    "outputs": {
        "controlPlaneFQDN": {
            "type": "string",
            "value": "[reference(concat('Microsoft.ContainerService/managedClusters/', parameters('resourceName'))).fqdn]"
        }
    }
}